superllm/__init__.py
superllm/core/__init__.py
superllm/core/expert_feedback.py
superllm/core/thought_tree.py
superllm/search/__init__.py
superllm/search/beam_search.py
superllm-0.1.0.dist-info/METADATA
superllm-0.1.0.dist-info/WHEEL
superllm-0.1.0.dist-info/top_level.txt
superllm-0.1.0.dist-info/RECORD
